realpy/__init__.py
realpy/stage.py
realpy/asset/__init__.py
realpy/asset/instance.py
realpy/asset/room.py
realpy/audio/__init__.py
realpy/core/__init__.py
realpy/core/function_input.py
realpy/core/function_instance.py
realpy/core/function_scene.py
realpy/core/arithmetic/__init__.py
realpy/core/behavior/__init__.py
realpy/core/behavior/actor.py
realpy/core/behavior/instance.py
realpy/core/collisionfield/__init__.py
realpy/core/constants/__init__.py
realpy/core/constants/header.py
realpy/core/framework/__init__.py
realpy/core/framework/header.py
realpy/core/image/__init__.py
realpy/core/layer/__init__.py
realpy/core/preset/__init__.py
realpy/core/preset/header.py
realpy/core/scene/__init__.py
realpy/core/sound/__init__.py
realpy/core/sound/header.py
realpy/core/sound/sfx/__init__.py
realpy/core/sprite/__init__.py
realpy/framework/__init__.py
realpy/framework/header.py
realpy/image/__init__.py
realpy/image/header.py
realpy/layer/__init__.py
realpy/layer/header.py
realpy/prefab/__init__.py
realpy/prefab/header.py
realpy/prefab/instance.py
realpy/preset/__init__.py
realpy/preset/header.py
realpy/scene/__init__.py
realpy/scene/header.py
realpy/sprite/__init__.py
realpy/sprite/header.py
realpy/utility/__init__.py
realpy/utility/header.py
realpy/view/__init__.py
realpy_engine_iconer-1.0.0.dist-info/LICENSE
realpy_engine_iconer-1.0.0.dist-info/METADATA
realpy_engine_iconer-1.0.0.dist-info/WHEEL
realpy_engine_iconer-1.0.0.dist-info/top_level.txt
realpy_engine_iconer-1.0.0.dist-info/RECORD
