Metadata-Version: 2.1
Name: realpy-engine-iconer
Version: 1.0.0
Summary: 2D game engine with pygame
Home-page: https://github.com/RealPy-Engine/realpy-core
Author: Iconerworks
Author-email: yoyofa2@hotmail.com
License: LICENSE
Project-URL: Bug Tracker, https://github.com/RealPy-Engine/realpy-core/issues
Platform: UNKNOWN
Classifier: Programming Language :: Python :: 3
Classifier: Programming Language :: Python :: 3.9
Classifier: Development Status :: 5 - Production/Stable
Classifier: Operating System :: OS Independent
Requires-Python: >=3.9
